setup.py
fallball/__init__.py
fallball/manage.py
fallball.egg-info/PKG-INFO
fallball.egg-info/SOURCES.txt
fallball.egg-info/dependency_links.txt
fallball.egg-info/top_level.txt