Metadata-Version: 1.0
Name: fallball
Version: 0.1
Summary: Dummy file sharing service available by REST api.
Home-page: http://fallball.io
Author: romanovskyj
Author-email: eromanovskyj@odin.com
License: Apache License
Platform: UNKNOWN
